pprint_torrent.py
pprint_torrent-1.0.0.dist-info/METADATA
pprint_torrent-1.0.0.dist-info/WHEEL
pprint_torrent-1.0.0.dist-info/entry_points.txt
pprint_torrent-1.0.0.dist-info/top_level.txt
pprint_torrent-1.0.0.dist-info/RECORD
