Metadata-Version: 2.1
Name: pprint-torrent
Version: 1.0.0
Summary: Pretty-print the contents of torrent files!
Home-page: https://github.com/rsnitsch/pprint_torrent
Author: Robert Nitsch
Author-email: mail@robertnitsch.de
Project-URL: Bug Reports, https://github.com/rsnitsch/pprint_torrent/issues
Project-URL: Source, https://github.com/rsnitsch/pprint_torrent
Keywords: torrents,commandline,shell,script
Classifier: Development Status :: 5 - Production/Stable
Classifier: Environment :: Console
Classifier: Intended Audience :: End Users/Desktop
Classifier: Intended Audience :: System Administrators
Classifier: Topic :: Communications :: File Sharing
Classifier: Programming Language :: Python :: 3
Classifier: Programming Language :: Python :: 3.8
Classifier: Programming Language :: Python :: 3.9
Classifier: Programming Language :: Python :: 3.10
Classifier: Programming Language :: Python :: 3.11
Classifier: Programming Language :: Python :: 3 :: Only
Requires-Python: >=3.8, <4
Requires-Dist: bencode.py
